mozfile/__init__.py
mozfile/mozfile.py
mozfile-2.0.0.dist-info/METADATA
mozfile-2.0.0.dist-info/RECORD
mozfile-2.0.0.dist-info/WHEEL
mozfile-2.0.0.dist-info/top_level.txt
